hyperon_das/__init__.py
hyperon_das/api.py
hyperon_das/das.py
hyperon_das/exceptions.py
hyperon_das/factory.py
hyperon_das/logger.py
hyperon_das/pattern_matcher/__init__.py
hyperon_das/pattern_matcher/constants.py
hyperon_das/pattern_matcher/pattern_matcher.py
hwtgwrtw_wertghwrthw-0.1.5.dist-info/METADATA
hwtgwrtw_wertghwrthw-0.1.5.dist-info/WHEEL
hwtgwrtw_wertghwrthw-0.1.5.dist-info/RECORD
